{"version":1,"resource":"file:///home/dave/hslu/SEM3/REVE1/assignments/assignment-3-assembly-lab/report.md","entries":[{"id":"ydiX.md","timestamp":1707322241900},{"id":"pbhW.md","timestamp":1707322284370},{"id":"3LOo.md","timestamp":1707322333874},{"id":"X00D.md","timestamp":1707322371640},{"id":"7unp.md","timestamp":1707326279970},{"id":"gmKv.md","timestamp":1707326519564},{"id":"6wvm.md","timestamp":1707326534230},{"id":"mEko.md","timestamp":1707326784407},{"id":"iiZt.md","timestamp":1707326991390},{"id":"750l.md","timestamp":1707327111530},{"id":"AI3t.md","timestamp":1707328004627},{"id":"JeTz.md","timestamp":1707328564194},{"id":"rW33.md","timestamp":1707328624580},{"id":"SX8o.md","timestamp":1707328707777},{"id":"mTv5.md","timestamp":1707328764267},{"id":"kg7q.md","timestamp":1707329673737},{"id":"ZrSe.md","timestamp":1707329995450},{"id":"LeNe.md","timestamp":1707330074450},{"id":"VrkQ.md","timestamp":1707330212387},{"id":"pf8Z.md","timestamp":1707330355624},{"id":"V2F6.md","timestamp":1707330384710},{"id":"eVLU.md","timestamp":1707330624297},{"id":"tW2x.md","timestamp":1707330657964},{"id":"CzyL.md","timestamp":1707330762274},{"id":"i6p6.md","timestamp":1707331149100},{"id":"6LLC.md","timestamp":1707331574317},{"id":"ANcU.md","timestamp":1707331822227},{"id":"PmLt.md","timestamp":1707332008184},{"id":"s5ny.md","timestamp":1707332187654},{"id":"wScP.md","timestamp":1707332265024},{"id":"iuAE.md","timestamp":1707332774387},{"id":"dDlf.md","timestamp":1707332859257},{"id":"2aGR.md","timestamp":1707332891587},{"id":"Fu2B.md","timestamp":1707333721763},{"id":"qQ38.md","timestamp":1707334089063}]}