{"version":1,"resource":"file:///home/dave/Desktop/hurti-hurti/java/Main.java","entries":[{"id":"oedb.java","source":"undoRedo.source","timestamp":1713952160487},{"id":"GnKv.java","source":"renamed.source","timestamp":1713952161357},{"id":"OJ7G.java","timestamp":1713952171941},{"id":"afBE.java","source":"Import 'StandardCharsets' (java.nio.charset)","timestamp":1713952181291},{"id":"Sb2P.java","source":"Import 'Base64' (java.util)","timestamp":1713952196048},{"id":"8hbK.java","timestamp":1713952271369},{"id":"ZqPS.java","timestamp":1713952294189},{"id":"TQKv.java","timestamp":1713952332390},{"id":"IEQV.java","timestamp":1713952358587},{"id":"7ueP.java","source":"undoRedo.source","timestamp":1713952396180},{"id":"lnKA.java","timestamp":1713952439894},{"id":"Jm9w.java","timestamp":1713955730151}]}